LeetcodeQuanjieDoocsKaiyuanShequFix1/README.md
LeetcodeQuanjieDoocsKaiyuanShequFix1/__init__.py
LeetcodeQuanjieDoocsKaiyuanShequFix1/__main__.py
LeetcodeQuanjieDoocsKaiyuanShequFix1/file.epub
LeetcodeQuanjieDoocsKaiyuanShequFix1/index.html
LeetcodeQuanjieDoocsKaiyuanShequFix1/css/__init__.py
LeetcodeQuanjieDoocsKaiyuanShequFix1/css/annotations.css
LeetcodeQuanjieDoocsKaiyuanShequFix1/css/main.css
LeetcodeQuanjieDoocsKaiyuanShequFix1/css/normalize.css
LeetcodeQuanjieDoocsKaiyuanShequFix1/css/popup.css
LeetcodeQuanjieDoocsKaiyuanShequFix1/font/__init__.py
LeetcodeQuanjieDoocsKaiyuanShequFix1/font/fontello.eot
LeetcodeQuanjieDoocsKaiyuanShequFix1/font/fontello.svg
LeetcodeQuanjieDoocsKaiyuanShequFix1/font/fontello.ttf
LeetcodeQuanjieDoocsKaiyuanShequFix1/font/fontello.woff
LeetcodeQuanjieDoocsKaiyuanShequFix1/img/__init__.py
LeetcodeQuanjieDoocsKaiyuanShequFix1/img/annotator-glyph-sprite.png
LeetcodeQuanjieDoocsKaiyuanShequFix1/img/annotator-icon-sprite.png
LeetcodeQuanjieDoocsKaiyuanShequFix1/img/apple-touch-icon.png
LeetcodeQuanjieDoocsKaiyuanShequFix1/img/cancelfullscreen.png
LeetcodeQuanjieDoocsKaiyuanShequFix1/img/close.png
LeetcodeQuanjieDoocsKaiyuanShequFix1/img/fullscreen.png
LeetcodeQuanjieDoocsKaiyuanShequFix1/img/loader.gif
LeetcodeQuanjieDoocsKaiyuanShequFix1/img/menu-icon.png
LeetcodeQuanjieDoocsKaiyuanShequFix1/img/save.png
LeetcodeQuanjieDoocsKaiyuanShequFix1/img/saved.png
LeetcodeQuanjieDoocsKaiyuanShequFix1/img/settings-s.png
LeetcodeQuanjieDoocsKaiyuanShequFix1/img/settings.png
LeetcodeQuanjieDoocsKaiyuanShequFix1/img/star.png
LeetcodeQuanjieDoocsKaiyuanShequFix1/js/__init__.py
LeetcodeQuanjieDoocsKaiyuanShequFix1/js/epub.js
LeetcodeQuanjieDoocsKaiyuanShequFix1/js/epub.min.js
LeetcodeQuanjieDoocsKaiyuanShequFix1/js/epub.min.map
LeetcodeQuanjieDoocsKaiyuanShequFix1/js/hooks.min.js
LeetcodeQuanjieDoocsKaiyuanShequFix1/js/hooks.min.map
LeetcodeQuanjieDoocsKaiyuanShequFix1/js/reader.js
LeetcodeQuanjieDoocsKaiyuanShequFix1/js/reader.js.map
leetcode_quanjie_doocs_kaiyuan_shequ_fix1-2025.3.25.0.dist-info/METADATA
leetcode_quanjie_doocs_kaiyuan_shequ_fix1-2025.3.25.0.dist-info/WHEEL
leetcode_quanjie_doocs_kaiyuan_shequ_fix1-2025.3.25.0.dist-info/entry_points.txt
leetcode_quanjie_doocs_kaiyuan_shequ_fix1-2025.3.25.0.dist-info/top_level.txt
leetcode_quanjie_doocs_kaiyuan_shequ_fix1-2025.3.25.0.dist-info/RECORD
